sphinxext/pwa/__init__.py
sphinxext/pwa/pwa_service_files/workbox-config.js
sphinxext_pwa-0.0.3a0.dist-info/LICENSE.md
sphinxext_pwa-0.0.3a0.dist-info/METADATA
sphinxext_pwa-0.0.3a0.dist-info/WHEEL
sphinxext_pwa-0.0.3a0.dist-info/top_level.txt
sphinxext_pwa-0.0.3a0.dist-info/RECORD
