Metadata-Version: 2.1
Name: sphinxext-pwa
Version: 0.0.3a0
Summary: Sphinx Extension to turn Sphinx websites into Progressive Web Applications
Home-page: https://github.com/wpilibsuite/sphinxext-pwa
Author: WPILib
Author-email: developers@wpilib.org
License: UNKNOWN
Platform: UNKNOWN
Classifier: Development Status :: 5 - Production/Stable
Classifier: Environment :: Plugins
Classifier: Environment :: Web Environment
Classifier: Framework :: Sphinx :: Extension
Classifier: Intended Audience :: Developers
Classifier: License :: OSI Approved :: MIT License
Classifier: Natural Language :: English
Classifier: Operating System :: OS Independent
Classifier: Programming Language :: Python :: 3.8
Classifier: Programming Language :: Python
Classifier: Topic :: Documentation :: Sphinx
Classifier: Topic :: Documentation
Classifier: Topic :: Software Development :: Documentation
Classifier: Topic :: Text Processing
Classifier: Topic :: Utilities
Requires-Python: >=3.8
Requires-Dist: sphinx (>=2.0)
